LICENSE
README.md
setup.cfg
setup.py
voicegain_speech/__init__.py
voicegain_speech/api_client.py
voicegain_speech/configuration.py
voicegain_speech/exceptions.py
voicegain_speech/rest.py
voicegain_speech.egg-info/PKG-INFO
voicegain_speech.egg-info/SOURCES.txt
voicegain_speech.egg-info/dependency_links.txt
voicegain_speech.egg-info/requires.txt
voicegain_speech.egg-info/top_level.txt
voicegain_speech/api/__init__.py
voicegain_speech/api/aivr_callback_api.py
voicegain_speech/api/aivr_ws_api.py
voicegain_speech/api/asr_callback_api.py
voicegain_speech/api/audiocodes_api.py
voicegain_speech/api/data_api.py
voicegain_speech/api/greg_api.py
voicegain_speech/api/meeting_api.py
voicegain_speech/api/recognize_api.py
voicegain_speech/api/sa_api.py
voicegain_speech/api/sa_internal_api.py
voicegain_speech/api/sa_offline_api.py
voicegain_speech/api/security_api.py
voicegain_speech/api/text_api.py
voicegain_speech/api/training_api.py
voicegain_speech/api/transcribe_api.py
voicegain_speech/api/websocket_api.py
voicegain_speech/models/__init__.py
voicegain_speech/models/ac_control_messages.py
voicegain_speech/models/ac_end.py
voicegain_speech/models/ac_error.py
voicegain_speech/models/ac_hypothesis.py
voicegain_speech/models/ac_hypothesis_alternatives.py
voicegain_speech/models/ac_recognition.py
voicegain_speech/models/ac_recognition_alternatives.py
voicegain_speech/models/ac_response_messages.py
voicegain_speech/models/ac_start.py
voicegain_speech/models/ac_start_stt_speech_contexts.py
voicegain_speech/models/ac_started.py
voicegain_speech/models/ac_stop.py
voicegain_speech/models/account_and_context_id.py
voicegain_speech/models/advanced_regex.py
voicegain_speech/models/agent.py
voicegain_speech/models/agent_all_of.py
voicegain_speech/models/agent_base.py
voicegain_speech/models/aircall.py
voicegain_speech/models/aircall_all_of.py
voicegain_speech/models/aivr.py
voicegain_speech/models/aivr_all_of.py
voicegain_speech/models/aivr_all_of_aivr_apps.py
voicegain_speech/models/aivr_app_data_item.py
voicegain_speech/models/aivr_callback_core_response.py
voicegain_speech/models/aivr_callback_core_response_all_of.py
voicegain_speech/models/aivr_callback_init_response.py
