Metadata-Version: 2.1
Name: voicegain-speech
Version: 1.130.0
Summary: Voicegain Speech-to-Text Python SDK
Home-page: UNKNOWN
Author: Huishen Zhan, Kuo Zhang, Jacek Jarmulak
Author-email: huishen@voicegain.ai, kuo@voicegain.ai, jacek@voicegain.ai
License: UNKNOWN
Download-URL: https://github.com/voicegain/python-sdk/archive/refs/tags/1.130.0.tar.gz
Platform: UNKNOWN
License-File: LICENSE
